[
  {
    "id": "5364972d-3a9d-4aeb-be58-6e301966cc9c",
    "data": [
      {
        "text": "thanks but no",
        "userDefined": false
      }
    ],
    "isTemplate": false,
    "count": 0,
    "updated": 0
  },
  {
    "id": "ca4dace0-bf05-46ca-b19e-12f6f3cc0649",
    "data": [
      {
        "text": "no way",
        "userDefined": false
      }
    ],
    "isTemplate": false,
    "count": 0,
    "updated": 0
  },
  {
    "id": "c40e040c-ebd6-41e4-91f2-a382d1eb350b",
    "data": [
      {
        "text": "no",
        "userDefined": false
      }
    ],
    "isTemplate": false,
    "count": 2,
    "updated": 0
  },
  {
    "id": "008686d5-4e79-4604-ab19-b69750ff742a",
    "data": [
      {
        "text": "no no don\u0027t",
        "userDefined": false
      }
    ],
    "isTemplate": false,
    "count": 0,
    "updated": 0
  },
  {
    "id": "21f806d7-5733-4dd2-9c38-a7d63db698c6",
    "data": [
      {
        "text": "na",
        "userDefined": false
      }
    ],
    "isTemplate": false,
    "count": 0,
    "updated": 0
  },
  {
    "id": "0a941766-4d7a-41ae-816b-695156b2b3eb",
    "data": [
      {
        "text": "no it isn\u0027t",
        "userDefined": false
      }
    ],
    "isTemplate": false,
    "count": 1,
    "updated": 0
  },
  {
    "id": "a1cabb60-eb14-4175-953f-35343010819d",
    "data": [
      {
        "text": "don\u0027t",
        "userDefined": false
      }
    ],
    "isTemplate": false,
    "count": 0,
    "updated": 0
  },
  {
    "id": "6209357a-3ef6-4582-b3ac-c29bccc6628b",
    "data": [
      {
        "text": "nah I\u0027m good",
        "userDefined": false
      }
    ],
    "isTemplate": false,
    "count": 1,
    "updated": 0
  },
  {
    "id": "be78496c-6a00-435d-bfee-1073219bf171",
    "data": [
      {
        "text": "no I cannot",
        "userDefined": false
      }
    ],
    "isTemplate": false,
    "count": 1,
    "updated": 0
  },
  {
    "id": "8b7acf0b-15e5-4b7c-adec-16608e1a1dcf",
    "data": [
      {
        "text": "I can\u0027t",
        "userDefined": false
      }
    ],
    "isTemplate": false,
    "count": 0,
    "updated": 0
  },
  {
    "id": "eddd7060-ad04-4baa-b126-51588b0546a2",
    "data": [
      {
        "text": "nothing",
        "userDefined": false
      }
    ],
    "isTemplate": false,
    "count": 0,
    "updated": 0
  },
  {
    "id": "f75072e6-8e5c-4723-9f2e-1a849b7ca135",
    "data": [
      {
        "text": "no that\u0027s okay",
        "userDefined": false
      }
    ],
    "isTemplate": false,
    "count": 0,
    "updated": 0
  },
  {
    "id": "2fa5c3ca-7365-458e-9f2b-4cb3ed72af7a",
    "data": [
      {
        "text": "no not really",
        "userDefined": false
      }
    ],
    "isTemplate": false,
    "count": 0,
    "updated": 0
  },
  {
    "id": "67139bf7-e87b-4b65-b892-808686496010",
    "data": [
      {
        "text": "nope not really",
        "userDefined": false
      }
    ],
    "isTemplate": false,
    "count": 0,
    "updated": 0
  },
  {
    "id": "70143bc3-c4b1-4f3e-9737-4e896b3288fd",
    "data": [
      {
        "text": "nope",
        "userDefined": false
      }
    ],
    "isTemplate": false,
    "count": 1,
    "updated": 0
  },
  {
    "id": "4a32b866-7d2b-4f96-ae5e-d3a49ef2b784",
    "data": [
      {
        "text": "thanks but not this time",
        "userDefined": false
      }
    ],
    "isTemplate": false,
    "count": 1,
    "updated": 0
  },
  {
    "id": "2b271792-de6c-44c0-bc93-89db0a2acd92",
    "data": [
      {
        "text": "I don\u0027t think so",
        "userDefined": false
      }
    ],
    "isTemplate": false,
    "count": 1,
    "updated": 0
  },
  {
    "id": "59c47f50-2bbb-4225-bd3a-fdd30323ebca",
    "data": [
      {
        "text": "I disagree",
        "userDefined": false
      }
    ],
    "isTemplate": false,
    "count": 2,
    "updated": 0
  },
  {
    "id": "df9ca3ef-2932-40c9-b129-4d364c57750a",
    "data": [
      {
        "text": "no maybe next time",
        "userDefined": false
      }
    ],
    "isTemplate": false,
    "count": 0,
    "updated": 0
  },
  {
    "id": "f9889229-9a60-4e51-a550-b72e5e533e17",
    "data": [
      {
        "text": "not this time",
        "userDefined": false
      }
    ],
    "isTemplate": false,
    "count": 0,
    "updated": 0
  },
  {
    "id": "05d13f6e-5577-4bda-854d-28407817094a",
    "data": [
      {
        "text": "no don\u0027t",
        "userDefined": false
      }
    ],
    "isTemplate": false,
    "count": 0,
    "updated": 0
  },
  {
    "id": "16c917dd-35df-4381-b39b-aacb32ffb212",
    "data": [
      {
        "text": "no we are good",
        "userDefined": false
      }
    ],
    "isTemplate": false,
    "count": 0,
    "updated": 0
  },
  {
    "id": "dd05de50-0c0d-4bef-9497-37202714befc",
    "data": [
      {
        "text": "don\u0027t do it",
        "userDefined": false
      }
    ],
    "isTemplate": false,
    "count": 3,
    "updated": 0
  },
  {
    "id": "1df7a95a-3f42-4693-8c60-5d7f6886995f",
    "data": [
      {
        "text": "no that\u0027s be all",
        "userDefined": false
      }
    ],
    "isTemplate": false,
    "count": 0,
    "updated": 0
  },
  {
    "id": "2f35056d-92f8-42af-a96a-7f00c1acdf67",
    "data": [
      {
        "text": "not right now",
        "userDefined": false
      }
    ],
    "isTemplate": false,
    "count": 0,
    "updated": 0
  },
  {
    "id": "b1e612e6-7835-4ab4-9d2d-0a28109c4bae",
    "data": [
      {
        "text": "nothing else thanks",
        "userDefined": false
      }
    ],
    "isTemplate": false,
    "count": 0,
    "updated": 0
  },
  {
    "id": "c740c61a-aced-45e5-8d5c-1c7cf399e3bb",
    "data": [
      {
        "text": "no thanks",
        "userDefined": false
      }
    ],
    "isTemplate": false,
    "count": 0,
    "updated": 0
  },
  {
    "id": "3a6899e0-c278-4629-a523-c9460f3eba2f",
    "data": [
      {
        "text": "no that\u0027s ok",
        "userDefined": false
      }
    ],
    "isTemplate": false,
    "count": 1,
    "updated": 0
  },
  {
    "id": "e9b6b518-9f38-46cf-89ad-42bfca3fdaad",
    "data": [
      {
        "text": "I don\u0027t want that",
        "userDefined": false
      }
    ],
    "isTemplate": false,
    "count": 0,
    "updated": 0
  },
  {
    "id": "9b2dc112-56ee-44f0-b07b-e82063d35ade",
    "data": [
      {
        "text": "definitely not",
        "userDefined": false
      }
    ],
    "isTemplate": false,
    "count": 3,
    "updated": 0
  },
  {
    "id": "27936008-bcff-4de6-a41c-667054b28a5f",
    "data": [
      {
        "text": "nothing else",
        "userDefined": false
      }
    ],
    "isTemplate": false,
    "count": 1,
    "updated": 0
  },
  {
    "id": "34440b0e-d6f9-4892-95ac-971d18ebbefd",
    "data": [
      {
        "text": "not",
        "userDefined": false
      }
    ],
    "isTemplate": false,
    "count": 0,
    "updated": 0
  },
  {
    "id": "7220ee38-8c99-4726-afd3-c35c6736c4d6",
    "data": [
      {
        "text": "not at all",
        "userDefined": false
      }
    ],
    "isTemplate": false,
    "count": 0,
    "updated": 0
  },
  {
    "id": "ddbdaf9d-99f3-4e4b-99e0-743fd16b5fd1",
    "data": [
      {
        "text": "no never",
        "userDefined": false
      }
    ],
    "isTemplate": false,
    "count": 0,
    "updated": 0
  },
  {
    "id": "6f10f950-35b8-476a-af55-4f88a4118757",
    "data": [
      {
        "text": "never",
        "userDefined": false
      }
    ],
    "isTemplate": false,
    "count": 0,
    "updated": 0
  },
  {
    "id": "6e14c48b-ae2f-4173-9ddc-3babbc4f753c",
    "data": [
      {
        "text": "no way no",
        "userDefined": false
      }
    ],
    "isTemplate": false,
    "count": 0,
    "updated": 0
  },
  {
    "id": "f26b0deb-110e-4d10-b6a9-1da484424d6f",
    "data": [
      {
        "text": "not really",
        "userDefined": false
      }
    ],
    "isTemplate": false,
    "count": 0,
    "updated": 0
  },
  {
    "id": "522485d3-0e75-4249-ac67-cdbd0caf957d",
    "data": [
      {
        "text": "nah",
        "userDefined": false
      }
    ],
    "isTemplate": false,
    "count": 2,
    "updated": 0
  },
  {
    "id": "9bdd4e53-4bae-4a5b-a1d7-fb8cd79cfd52",
    "data": [
      {
        "text": "I don\u0027t",
        "userDefined": false
      }
    ],
    "isTemplate": false,
    "count": 0,
    "updated": 0
  },
  {
    "id": "5d62c2b0-b552-41a8-9fbe-b9a559fb00d1",
    "data": [
      {
        "text": "I don\u0027t want",
        "userDefined": false
      }
    ],
    "isTemplate": false,
    "count": 0,
    "updated": 0
  },
  {
    "id": "a4e818c7-29ed-45af-909f-b40a5a204e88",
    "data": [
      {
        "text": "not ",
        "userDefined": false
      },
      {
        "text": "today",
        "meta": "@sys.ignore",
        "userDefined": false
      }
    ],
    "isTemplate": false,
    "count": 0,
    "updated": 0
  },
  {
    "id": "99641cf7-7200-49ab-acb0-ee76f00420d9",
    "data": [
      {
        "text": "not interested",
        "userDefined": false
      }
    ],
    "isTemplate": false,
    "count": 0,
    "updated": 0
  },
  {
    "id": "119a69ff-fa4b-48b5-b0a4-fd628bb52bf4",
    "data": [
      {
        "text": "no that\u0027s fine thank you",
        "userDefined": false
      }
    ],
    "isTemplate": false,
    "count": 0,
    "updated": 0
  },
  {
    "id": "0534edd3-ff1d-44a3-a67e-718042b9ae7b",
    "data": [
      {
        "text": "I\u0027m not",
        "userDefined": false
      }
    ],
    "isTemplate": false,
    "count": 3,
    "updated": 0
  }
]